lime/__init__.py
lime/changelog.txt
lime/io.py
lime/lime.toml
lime/observations.py
lime/rsrc_manager.py
lime/tools.py
lime/transitions.py
lime/workflow.py
lime/archives/__init__.py
lime/archives/read_fits.py
lime/archives/tables.py
lime/fitting/__init__.py
lime/fitting/lines.py
lime/fitting/redshift.py
lime/inference/detection.py
lime/inference/intensity_threshold.py
lime/plotting/__init__.py
lime/plotting/bokeh_plots.py
lime/plotting/format.py
lime/plotting/plots.py
lime/plotting/plots_interactive.py
lime/plotting/theme_lime.toml
lime/plotting/utils.py
lime/resources/__init__.py
lime/resources/generator_db.py
lime/resources/generator_logo.py
lime/resources/lines_database_v2.0.0.txt
lime/resources/types_params.txt
lime/retrieve/__init__.py
lime/retrieve/line_bands.py
lime_stable-2.0.5.dist-info/licenses/LICENSE.rst
lime_stable-2.0.5.dist-info/METADATA
lime_stable-2.0.5.dist-info/WHEEL
lime_stable-2.0.5.dist-info/top_level.txt
lime_stable-2.0.5.dist-info/RECORD
