Metadata-Version: 2.4
Name: lime-stable
Version: 2.0.5
Summary: Line measuring algorithm for astronomical spectra
Author-email: Vital Fernández <vgf@stsci.edu>
License: GPL-3.0-or-later
Classifier: License :: OSI Approved :: GNU General Public License v3 (GPLv3)
Classifier: Programming Language :: Python :: 3.11
Requires-Python: >=3.11
License-File: LICENSE.rst
Requires-Dist: astropy~=7.1
Requires-Dist: lmfit~=1.3
Requires-Dist: matplotlib~=3.10
Requires-Dist: numpy~=2.3
Requires-Dist: pandas~=2.2
Requires-Dist: scipy~=1.16
Requires-Dist: tomli>=2.0.0; python_version < "3.11"
Provides-Extra: full
Requires-Dist: asdf~=4.1; extra == "full"
Requires-Dist: aspect-stable~=0.5.1; extra == "full"
Requires-Dist: bokeh~=3.8; extra == "full"
Requires-Dist: mplcursors~=0.6; extra == "full"
Requires-Dist: openpyxl~=3.1; extra == "full"
Requires-Dist: PyLaTeX~=1.4; extra == "full"
Requires-Dist: toml~=0.10; extra == "full"
Provides-Extra: docs
Requires-Dist: sphinx-rtd-theme~=3.0; extra == "docs"
Requires-Dist: sphinx_togglebutton~=0.3; extra == "docs"
Requires-Dist: sphinx_book_theme~=1.1; extra == "docs"
Requires-Dist: ipympl~=0.9; extra == "docs"
Requires-Dist: myst-nb~=1.3; extra == "docs"
Provides-Extra: tests
Requires-Dist: pytest~=8.4; extra == "tests"
Requires-Dist: pytest-cov~=7.0; extra == "tests"
Requires-Dist: pytest-mpl~=0.17; extra == "tests"
Dynamic: license-file
